test_proj/__init__.py
test_proj/py.typed
test_proj/util.py
testpeepoo-1.0.0.dist-info/LICENSE
testpeepoo-1.0.0.dist-info/METADATA
testpeepoo-1.0.0.dist-info/WHEEL
testpeepoo-1.0.0.dist-info/top_level.txt
testpeepoo-1.0.0.dist-info/RECORD
