Metadata-Version: 2.1
Name: testpeepoo
Version: 1.0.0
Summary: Test project
Author-email: Samarth Mistry <samarth.mistry@gmail.com>
License: Apache License
Classifier: License :: OSI Approved :: Apache Software License
Classifier: Development Status :: 5 - Production/Stable
Classifier: Intended Audience :: Developers
Classifier: Intended Audience :: Information Technology
Classifier: Intended Audience :: Science/Research
Classifier: Operating System :: OS Independent
Classifier: Programming Language :: Python
Classifier: Programming Language :: Python :: 3.10
Classifier: Programming Language :: Python :: 3.11
Classifier: Programming Language :: Python :: 3.12
Classifier: Typing :: Typed
Requires-Python: >=3.10
License-File: LICENSE
Provides-Extra: dev
Requires-Dist: ruff >=0.7.0 ; extra == 'dev'
Requires-Dist: pre-commit >=3.8.0 ; extra == 'dev'
Requires-Dist: tox >=4.14.1 ; extra == 'dev'
Requires-Dist: test-proj[tests] ; extra == 'dev'
Requires-Dist: test-proj[docs] ; extra == 'dev'
Provides-Extra: docs
Requires-Dist: Sphinx ==8.0.2 ; extra == 'docs'
Requires-Dist: numpydoc ==1.8.0 ; extra == 'docs'
Requires-Dist: ansys-sphinx-theme ==1.0.3 ; extra == 'docs'
Provides-Extra: tests
Requires-Dist: pytest >=8.1.1 ; extra == 'tests'
Requires-Dist: coverage >=7.4.4 ; extra == 'tests'
Requires-Dist: pytest-cov >=4.1.0 ; extra == 'tests'
Requires-Dist: pytest-randomly >=3.15.0 ; extra == 'tests'
Requires-Dist: mypy[faster-cache] >=1.13.0 ; extra == 'tests'
